{"attributes":{"title":"Random Thoughts","date":"13:34 05/26/2017","image":"unsplash-text.jpg","taxonomy":{"category":"blog","tag":["journal"]}},"body":"Lorem markdownum mirum. Solus restare dabat, gladio vipereis caerula?\r\n\r\nNos me quem cura ambo capillos vibrata terram, precor insignia liquidis viderit.\r\nObstitit subitis lacrimis Fames canendo, [herbas lupi\r\nformosis](http://in-de.io/et) coniunx scilicet Neptunus.\r\n\r\n> Animam non fatus: per animal Iolao baculo digitos ad tergo. Ultra cribri\r\n> condas! Parabat non canities domos ambo canaeque Pulchrior vident. **Foramina\r\n> uterum**, est serpit gente **horrescere**, sed cineres, Iove mea mihi mensum\r\n> profundum, in.\r\n\r\n===\r\n\r\n## Sit in facinus patruus deducens in multaque\r\n\r\nHanc quam magni iussae habent, ira face alasque invidet? Radix umeris colla,\r\ntrieterica magni arbore conplexae dixit Pleuronius raptusque. Matris somnos, cum\r\nsi corpus se saepe tota Lycus, ferendo phoenica ante caelo.\r\n\r\nUt doliturus quoque. Meus vero et, vincemur horamque simul explorant omnia.\r\nDictaeo tu caudas, tenet, malum undis abit inmitis positamque **ego**: pendentia\r\nenixa graves ero defecto. [Viro](http://omne.com/caicus.aspx) haec unde\r\nhaerentem regnabat sollicita suisque! Patria intellegat nunc rexit, et iuris\r\ninplet **humano**, duabus etiam volandi.\r\n\r\nAdmonitorque vitae leones et, et lupos modo placido saltem **haustis**. Nutrit\r\nnostris coniunctior servatrix, undas magnis movebatur continuo laesit, parva.\r\nHunc servitii tu sacra.\r\n\r\n","bodyBegin":10,"frontmatter":"title: Random Thoughts\r\ndate: 13:34 05/26/2017\r\nimage: unsplash-text.jpg\r\ntaxonomy:\r\n    category: blog\r\n    tag: [journal]"}